mdance/__init__.py
mdance/_version.py
mdance/cli/__init__.py
mdance/cli/prime_rep.py
mdance/cli/prime_sim.py
mdance/cluster/__init__.py
mdance/cluster/divine.py
mdance/cluster/equal.py
mdance/cluster/helm.py
mdance/cluster/nani.py
mdance/cluster/shine.py
mdance/data/README.rst
mdance/data/__init__.py
mdance/data/aligned_1000_tau.dcd
mdance/data/aligned_original_tau_6K.dcd
mdance/data/aligned_tau.pdb
mdance/data/backbone.npy
mdance/data/blob_disk.csv
mdance/data/cc_sim.npy
mdance/data/diamond9.csv
mdance/data/ellipses.csv
mdance/data/labels_6.csv
mdance/data/labels_60.csv
mdance/data/labels_6_strat_all.csv
mdance/data/labels_6_strat_reduced.csv
mdance/data/trimmed_sim.npy
mdance/inputs/__init__.py
mdance/inputs/preprocess.py
mdance/outputs/__init__.py
mdance/outputs/postprocess.py
mdance/prime/__init__.py
mdance/prime/rep_frames.py
mdance/prime/sim_calc.py
mdance/tools/__init__.py
mdance/tools/bts.py
mdance/tools/esim.py
mdance/tools/isim.py
mdance-0.3.8.dist-info/licenses/AUTHORS.md
mdance-0.3.8.dist-info/licenses/LICENSE
mdance-0.3.8.dist-info/METADATA
mdance-0.3.8.dist-info/WHEEL
mdance-0.3.8.dist-info/entry_points.txt
mdance-0.3.8.dist-info/top_level.txt
mdance-0.3.8.dist-info/RECORD
