Metadata-Version: 2.4
Name: MDANCE
Version: 0.3.8
Summary: a flexible n-ary clustering package for all applications.
Author-email: Lexin Chen <le.chen@ufl.edu>
Project-URL: Homepage, https://github.com/mqcomplab/MDANCE
Project-URL: Documentation, https://mdance.readthedocs.io/en/latest/
Project-URL: Repository, https://github.com/mqcomplab/MDANCE
Project-URL: Issues, https://github.com/mqcomplab/MDANCE/issues
Classifier: Programming Language :: Python :: 3
Classifier: License :: OSI Approved :: MIT License
Classifier: Operating System :: OS Independent
Requires-Python: >=3.8
License-File: LICENSE
License-File: AUTHORS.md
Requires-Dist: numpy>=1.20.0
Requires-Dist: scikit-learn>=0.24.0
Requires-Dist: MDAnalysis>=2.0.0
Requires-Dist: shapeGMMTorch>=2.0.0
Requires-Dist: torch>=2.2.2
Provides-Extra: dev
Requires-Dist: pytest>=7.0; extra == "dev"
Dynamic: license-file
